scenedataset/__init__.py
scenedataset/scenedataset.py
scenedataset/utils.py
scenedataset-1.0.2.dist-info/LICENSE
scenedataset-1.0.2.dist-info/METADATA
scenedataset-1.0.2.dist-info/WHEEL
scenedataset-1.0.2.dist-info/RECORD
